[
  {
    "case_id": "failure_broad_gpu_anchor_top5_projection",
    "kind": "positive",
    "platform": "qq",
    "platform_channel_id": "905393941",
    "query": "这两天我们有讨论过显卡的话题嘛",
    "keywords": ["显卡"],
    "from_timestamp": "2026-05-09T12:00:00+00:00",
    "to_timestamp": "2026-05-11T11:59:59+00:00",
    "expected_any": ["Steam", "RTX 3060", "NVIDIA", "73.21"],
    "expected_message_ids": ["1587029525"],
    "forbidden_any": ["早餐外卖"]
  },
  {
    "case_id": "failure_wrong_utc_yesterday_window",
    "kind": "positive",
    "platform": "qq",
    "platform_channel_id": "905393941",
    "query": "昨天我们讨论过的显卡市场占有率的话题",
    "keywords": ["显卡", "市场份额", "steam"],
    "from_timestamp": "2026-05-10T00:00:00+00:00",
    "to_timestamp": "2026-05-11T00:00:00+00:00",
    "expected_any": ["Steam", "RTX 3060", "NVIDIA", "73.21"],
    "expected_message_ids": ["1587029525"],
    "forbidden_any": ["早餐外卖"]
  },
  {
    "case_id": "failure_literal_synonym_anchor_only",
    "kind": "positive",
    "platform": "qq",
    "platform_channel_id": "905393941",
    "query": "昨天我们讨论过的显卡市场占有率的话题",
    "keywords": ["市场占有率"],
    "from_timestamp": "2026-05-10T12:00:00+00:00",
    "to_timestamp": "2026-05-11T11:59:59+00:00",
    "expected_any": ["Steam", "RTX 3060", "NVIDIA", "73.21"],
    "expected_message_ids": ["1587029525"],
    "forbidden_any": ["早餐外卖"]
  },
  {
    "case_id": "failure_attachment_projection_xhs_remote_management",
    "kind": "positive",
    "platform": "qq",
    "platform_channel_id": "905393941",
    "query": "这两天群里有没有发类似小红书的远程管理截图",
    "keywords": ["小红书", "远程管理"],
    "from_timestamp": "2026-05-09T12:00:00+00:00",
    "to_timestamp": "2026-05-11T11:59:59+00:00",
    "expected_any": ["远程管理", "United States Department of the Navy", "小红书"],
    "expected_message_ids": ["412404912"],
    "forbidden_any": ["早餐外卖"]
  },
  {
    "case_id": "failure_attachment_projection_prusa_benchy",
    "kind": "positive",
    "platform": "qq",
    "platform_channel_id": "905393941",
    "query": "这两天群里有没有发 Prusa MK3S Klipper 8分钟 Benchy 的图",
    "keywords": ["Prusa", "Klipper", "Benchy"],
    "from_timestamp": "2026-05-09T12:00:00+00:00",
    "to_timestamp": "2026-05-11T11:59:59+00:00",
    "expected_any": ["Prusa MK3S", "Klipper", "Benchy", "8 分钟"],
    "expected_message_ids": ["52810436"],
    "forbidden_any": ["早餐外卖"]
  },
  {
    "case_id": "failure_attachment_projection_gpu_table",
    "kind": "positive",
    "platform": "qq",
    "platform_channel_id": "905393941",
    "query": "这两天群里有没有发 Steam 实际装机比例和 RTX 50 系列供应链的截图",
    "keywords": ["Steam", "RTX 50", "供应链"],
    "from_timestamp": "2026-05-09T12:00:00+00:00",
    "to_timestamp": "2026-05-11T11:59:59+00:00",
    "expected_any": ["Steam", "RTX 50", "供应链", "实际装机比例"],
    "expected_message_ids": ["1369111049"],
    "forbidden_any": ["早餐外卖"]
  },
  {
    "case_id": "failure_literal_trap_xhs_link",
    "kind": "negative",
    "platform": "qq",
    "platform_channel_id": "905393941",
    "query": "这两天群里有没有发小红书链接",
    "keywords": ["xhslink"],
    "from_timestamp": "2026-05-09T12:00:00+00:00",
    "to_timestamp": "2026-05-11T11:59:59+00:00",
    "expected_any": [],
    "expected_message_ids": [],
    "forbidden_any": ["远程管理", "United States Department of the Navy", "黄腿肠"]
  },
  {
    "case_id": "failure_absent_topic_semantic_drift",
    "kind": "negative",
    "platform": "qq",
    "platform_channel_id": "905393941",
    "query": "这两天群里有没有聊下雨带伞",
    "keywords": ["下雨", "带伞", "雨伞"],
    "from_timestamp": "2026-05-09T12:00:00+00:00",
    "to_timestamp": "2026-05-11T11:59:59+00:00",
    "expected_any": [],
    "expected_message_ids": [],
    "forbidden_any": ["RTX 3060", "显卡", "RAG", "打印机", "text-embedding-nomic-embed-text-v2-moe"]
  }
]
